README.md
setup.py
version.txt
dimmerattenuation.egg-info/PKG-INFO
dimmerattenuation.egg-info/SOURCES.txt
dimmerattenuation.egg-info/dependency_links.txt
dimmerattenuation.egg-info/requires.txt
dimmerattenuation.egg-info/top_level.txt
src/fortran/Reddening/CAF__LawOPT.f90
src/fortran/Reddening/CALR_LawOPT.f90
src/fortran/Reddening/CCMR_LawOPT.f90
src/fortran/Reddening/CL_R_LawOPT.f90
src/fortran/Reddening/DataTypes.f90
src/fortran/Reddening/H83gaLawOPT.f90
src/fortran/Reddening/J13__LawOPT.f90
src/fortran/Reddening/Leitherer02.f90
src/fortran/Reddening/O_Donnell94.f90
src/fortran/Reddening/S79__LawOPT.f90
src/fortran/Reddening/SPLINE1DArr.f90
src/python/Reddening.py
src/python/__init__.py