Metadata-Version: 2.1
Name: dimmerattenuation
Version: 0.0.1
Summary: DimmerAttenuation is a standalone python library with Fortran legacy routines for absorption (attenuation).
Home-page: https://github.com/neutrinomuon/DustyGlow
Author: Jean Gomes
Author-email: antineutrinomuon@gmail.com
Classifier: Programming Language :: Python :: 3
Classifier: Programming Language :: Fortran
Classifier: Operating System :: OS Independent
Requires-Dist: numpy
Requires-Dist: matplotlib
